mitoviz/__init__.py
mitoviz/constants.py
mitoviz/locus.py
mitoviz/mitoviz.py
mitoviz/parsers.py
mitoviz/plot.py
mitoviz/utils.py
mitoviz/variant.py
mitoviz-0.9.0.dist-info/AUTHORS.rst
mitoviz-0.9.0.dist-info/LICENSE
mitoviz-0.9.0.dist-info/METADATA
mitoviz-0.9.0.dist-info/WHEEL
mitoviz-0.9.0.dist-info/entry_points.txt
mitoviz-0.9.0.dist-info/top_level.txt
mitoviz-0.9.0.dist-info/RECORD
