Metadata-Version: 2.1
Name: mitoviz
Version: 0.9.0
Summary: Plot variants on the human mitochondrial genome.
Home-page: https://github.com/robertopreste/mitoviz
Author: Roberto Preste
Author-email: robertopreste@gmail.com
License: MIT license
Keywords: mitoviz
Platform: UNKNOWN
Classifier: Development Status :: 4 - Beta
Classifier: Intended Audience :: Developers
Classifier: License :: OSI Approved :: MIT License
Classifier: Natural Language :: English
Classifier: Programming Language :: Python :: 3
Classifier: Programming Language :: Python :: 3.6
Classifier: Programming Language :: Python :: 3.7
Requires-Dist: Click (>=7.0)
Requires-Dist: numpy
Requires-Dist: pandas
Requires-Dist: matplotlib
Requires-Dist: pysam
Requires-Dist: vcfpy
Requires-Dist: plotly
